[{"Rectitem":{"X":0,"Y":0,"Width":10,"Height":8},"Cam":null,"Cg":null,"Current":0,"PBX":null,"Treenode":null,"Bui":{"AutoSize":false,"AutoSizeMode":1,"AutoValidate":1,"BorderStyle":0,"Text":"","AutoScaleDimensions":"0, 0","AutoScaleMode":3,"BindingContext":[],"ActiveControl":null,"CurrentAutoScaleDimensions":"0, 0","ParentForm":{"rli":{"Xsteps":39,"Ysteps":39,"N":20,"Rlist":[{"X":0,"Y":0,"Width":10,"Height":8},{"X":10,"Y":0,"Width":11,"Height":8},{"X":21,"Y":0,"Width":12,"Height":8},{"X":0,"Y":8,"Width":10,"Height":8},{"X":10,"Y":8,"Width":11,"Height":8},{"X":21,"Y":8,"Width":12,"Height":8},{"X":0,"Y":16,"Width":33,"Height":4}]},"rlist":["0, 0, 10, 8","10, 0, 11, 8","21, 0, 12, 8","0, 8, 10, 8","10, 8, 11, 8","21, 8, 12, 8","0, 16, 33, 4"]